tasks_tui/__init__.py
tasks_tui/auth.py
tasks_tui/local_storage.py
tasks_tui/main.py
tasks_tui/task_service.py
tasks_tui/ui_manager.py
tasks_tui_app-0.1.6.dist-info/licenses/LICENSE
tasks_tui_app-0.1.6.dist-info/METADATA
tasks_tui_app-0.1.6.dist-info/WHEEL
tasks_tui_app-0.1.6.dist-info/entry_points.txt
tasks_tui_app-0.1.6.dist-info/top_level.txt
tasks_tui_app-0.1.6.dist-info/RECORD
