Metadata-Version: 2.4
Name: tasks-tui-app
Version: 0.1.6
Summary: A command-line TUI for managing Google Tasks.
Author-email: Huy Pham <huyquangpham2005@gmai.com>
License-Expression: MIT
Classifier: Programming Language :: Python :: 3
Classifier: Operating System :: OS Independent
Classifier: Environment :: Console :: Curses
License-File: LICENSE
Requires-Dist: google-api-python-client
Requires-Dist: google-auth-oauthlib
Requires-Dist: google-auth-httplib2
Dynamic: license-file
